foliage/__init__.py
foliage/contextmanagers.py
foliage/utils.py
foliage/tests/__init__.py
foliage/tests/settings.py
foliage/tests/test_contextmanagers.py
foliage/tests/test_utils.py
foliage/tests/testapp/__init__.py
foliage/tests/testapp/models.py
foliage/tests/testapp/urls.py
foliage/tests/testapp/migrations/0001_initial.py
foliage/tests/testapp/migrations/__init__.py
wagtail_foliage-0.1.1.dist-info/LICENSE
wagtail_foliage-0.1.1.dist-info/METADATA
wagtail_foliage-0.1.1.dist-info/WHEEL
wagtail_foliage-0.1.1.dist-info/top_level.txt
wagtail_foliage-0.1.1.dist-info/RECORD
