Metadata-Version: 2.1
Name: wagtail-foliage
Version: 0.1.1
Summary: Utilities for programatically constructing page trees in Wagtail
Home-page: https://github.com/harrislapiroff/wagtail-foliage
Author: Harris Lapiroff
Author-email: harris@freedom.press
License: BSD-3-Clause
Platform: UNKNOWN
Classifier: Development Status :: 4 - Beta
Classifier: Environment :: Web Environment
Classifier: Intended Audience :: Developers
Classifier: License :: OSI Approved :: BSD License
Classifier: Operating System :: OS Independent
Classifier: Programming Language :: Python
Classifier: Programming Language :: Python :: 2.7
Classifier: Programming Language :: Python :: 3.4
Classifier: Programming Language :: Python :: 3.5
Classifier: Programming Language :: Python :: 3.6
Classifier: Framework :: Django
Classifier: Framework :: Wagtail
Classifier: Framework :: Wagtail :: 1
Classifier: Framework :: Wagtail :: 2
Classifier: Topic :: Internet :: WWW/HTTP
Classifier: Topic :: Internet :: WWW/HTTP :: Dynamic Content
Requires-Dist: typing (>=3.6.6)
Requires-Dist: wagtail (>=1.11)
Provides-Extra: docs
Requires-Dist: Sphinx (>=1.7) ; extra == 'docs'
Requires-Dist: sphinx-rtd-theme (>=0.4.0) ; extra == 'docs'
Provides-Extra: test
Requires-Dist: tox ; extra == 'test'
Requires-Dist: pytest (>=3.5) ; extra == 'test'
Requires-Dist: pytest-django (>=3.2) ; extra == 'test'
Requires-Dist: pytest-pythonpath (>=0.7.2) ; extra == 'test'
